django_pwdtk-2.0.3.dist-info/licenses/LICENSE
pwdtk/__init__.py
pwdtk/admin.py
pwdtk/apps.py
pwdtk/auth_backends.py
pwdtk/auth_backends_settings.py
pwdtk/exceptions.py
pwdtk/helpers.py
pwdtk/middlewares.py
pwdtk/models.py
pwdtk/settings.py
pwdtk/signals.py
pwdtk/test_settings.py
pwdtk/testviews.py
pwdtk/validators.py
pwdtk/locale/fr/LC_MESSAGES/django.mo
pwdtk/locale/fr/LC_MESSAGES/django.po
pwdtk/migrations/0001_initial.py
pwdtk/migrations/0002_auto_20191105_1610.py
pwdtk/migrations/0003_auto_20191107_1501.py
pwdtk/migrations/0004_auto_20200304_1114.py
pwdtk/migrations/0005_auto_20200304_1116.py
pwdtk/migrations/0006_auto_20200304_1117.py
pwdtk/migrations/0007_auto_20200304_1139.py
pwdtk/migrations/0008_auto_20230905_0835.py
pwdtk/migrations/0009_auto_20250320_1409.py
pwdtk/migrations/0010_auto_20250328_0817.py
pwdtk/migrations/0011_alter_pwddata_password_history.py
pwdtk/migrations/0012_remove_pwddata_lockout_count.py
pwdtk/migrations/__init__.py
pwdtk/templates/login/locked_out_simple.html
pwdtk/templates/test/login.html
pwdtk/testproject/__init__.py
pwdtk/testproject/logcfg.py
pwdtk/testproject/manage22.py
pwdtk/testproject/manage31.py
pwdtk/testproject/manage42.py
pwdtk/testproject/pytest_runner.py
pwdtk/testproject/dj1/__init__.py
pwdtk/testproject/dj1/settings.py
pwdtk/testproject/dj1/urls.py
pwdtk/testproject/dj1/wsgi.py
pwdtk/testproject/dj21/__init__.py
pwdtk/testproject/dj21/settings.py
pwdtk/testproject/dj21/urls.py
pwdtk/testproject/dj21/wsgi.py
pwdtk/testproject/dj22/__init__.py
pwdtk/testproject/dj22/settings.py
pwdtk/testproject/dj22/urls.py
pwdtk/testproject/dj22/wsgi.py
pwdtk/testproject/dj31/__init__.py
pwdtk/testproject/dj31/settings.py
pwdtk/testproject/dj31/urls.py
pwdtk/testproject/dj31/wsgi.py
pwdtk/testproject/dj42/__init__.py
pwdtk/testproject/dj42/settings.py
pwdtk/testproject/dj42/urls.py
pwdtk/testproject/dj42/wsgi.py
pwdtk/tests/__init__.py
pwdtk/tests/fixtures.py
pwdtk/tests/test_login.py
pwdtk/tests/test_pwd_hash.py
pwdtk/tests/test_timezone.py
pwdtk/tests/test_validators.py
django_pwdtk-2.0.3.dist-info/METADATA
django_pwdtk-2.0.3.dist-info/WHEEL
django_pwdtk-2.0.3.dist-info/top_level.txt
django_pwdtk-2.0.3.dist-info/RECORD
