Metadata-Version: 2.4
Name: django-pwdtk
Version: 2.0.3
Summary: package to tune django password authentification
Home-page: https://github.com/mhcomm/django-pwdtk
Author: MHComm
Author-email: info@mhcomm.fr
License: MIT
Project-URL: Documentation, https://github.com/mhcomm/django-pwdtk
Project-URL: Source, https://github.com/mhcomm/django-pwdtk
Project-URL: SayThanks, https://github.com/mhcomm
Project-URL: Funding, https://donate.pypi.org
Project-URL: Tracker, https://github.com/mhcomm/django-pwdtk/issues
Keywords: django authentification password
Classifier: Development Status :: 3 - Alpha
Requires-Python: >=3.7, <4
License-File: LICENSE
Dynamic: author
Dynamic: author-email
Dynamic: classifier
Dynamic: home-page
Dynamic: keywords
Dynamic: license
Dynamic: license-file
Dynamic: project-url
Dynamic: requires-python
Dynamic: summary
